aboutdir-1.1.dist-info/WHEEL
aboutdir-1.1.dist-info/top_level.txt
aboutdir-1.1.dist-info/DESCRIPTION.rst
aboutdir-1.1.dist-info/RECORD
aboutdir-1.1.dist-info/METADATA
aboutdir-1.1.dist-info/entry_points.txt
aboutdir-1.1.dist-info/metadata.json
aboutdir/__init__.py
aboutdir/mains.py
