Metadata-Version: 2.0
Name: aboutdir
Version: 1.1
Summary: Command line tool for adding description to directories
Home-page: https://github.com/kousiksatish/about_directory
Author: Kousik Satish
Author-email: kousiksatish@gmail.com
License: UNKNOWN
Keywords: CLI,directory,aboutdir,about-directory,description-for-directory
Platform: UNKNOWN
Classifier: Programming Language :: Python :: 2
Classifier: Programming Language :: Python :: 2.6
Classifier: Programming Language :: Python :: 2.7
Classifier: Programming Language :: Python :: 3
Classifier: Programming Language :: Python :: 3.2
Classifier: Programming Language :: Python :: 3.3
Classifier: Programming Language :: Python :: 3.4
